dbml_sqlite/__init__.py
dbml_sqlite/core.py
dbml_sqlite/terminal.py
dbml_sqlite-0.3.2.dist-info/entry_points.txt
dbml_sqlite-0.3.2.dist-info/LICENSE.md
dbml_sqlite-0.3.2.dist-info/WHEEL
dbml_sqlite-0.3.2.dist-info/METADATA
dbml_sqlite-0.3.2.dist-info/RECORD
